{
  "dn11:9-66.1": "Furthermore, a Realized One arises in the world … ",
  "dn11:9-66.2": "That’s how a mendicant is accomplished in ethics. … ",
  "dn11:9-66.3": "They enter and remain in the first absorption … ",

# "1st combined refrain VIRTUAL-ANCHOR dn11:9-66.4",

  "dn11:9-66.5": "They enter and remain in the second absorption … ",
  "dn11:9-66.6": "third absorption … ",
  "dn11:9-66.7": "fourth absorption. ",

# "4th combined refrain VIRTUAL-ANCHOR dn11:9-66.8",

  "dn11:9-66.9": "They project and extend the mind toward knowledge and vision … ",

# "5th combined refrain VIRTUAL-ANCHOR dn11:9-66.10",

  "dn11:9-66.11": "They understand: ‘… there is nothing further for this place.’ ",

# "12th combined refrain (outside of ambit)"
}


# "1st combined refrain VIRTUAL-ANCHOR dn11:9-66.4",
  "dn11:9-66.4": "This is called the demonstration of instruction. ",

# "4th combined refrain VIRTUAL-ANCHOR dn11:9-66.8  (remap-target for 2nd & 3rd combined refrains)",
  "dn11:9-66.8": "This too is called the demonstration of instruction. ",

# "5th combined refrain VIRTUAL-ANCHOR dn11:9-66.10 (remap-target for 6th thru 11th combined refrains)",
  "dn11:9-66.10": "This too is called the demonstration of instruction. ",

